LICENSE
MANIFEST.in
README.rst
setup.py
django_nomad_activity_feed.egg-info/PKG-INFO
django_nomad_activity_feed.egg-info/SOURCES.txt
django_nomad_activity_feed.egg-info/dependency_links.txt
django_nomad_activity_feed.egg-info/top_level.txt
feeds/__init__.py
feeds/admin.py
feeds/mixins.py
feeds/models.py
feeds/tests.py
feeds/urls.py
feeds/views.py
feeds/templates/feeds/bits/follow_category_btn_sample.html
feeds/templatetags/__init__.py
feeds/templatetags/feed_tags.py